Counter/counter.v
module counter_basic (
    input clk,
    input rst,
    output [7:0] count
);

    reg [7:0] count_temp;

    always @(posedge clk) begin
        if (!rst)
            count_temp <= 8'd0;
        else
            count_temp <= count_temp + 1;
    end

    assign count = count_temp;

endmodule

Counter/counter_tb.v
`timescale 1ns/1ps
module counter_basic_tb;

    reg clk;
    reg rst;
    wire [7:0] count;

    // Instantiate DUT
    counter_basic uut (
        .clk(clk),
        .rst(rst),
        .count(count)
    );

    // Clock generator: 10ns period
    always #5 clk = ~clk;

    initial begin
        // Initialize
        clk = 0;
        rst = 0;

        // Apply reset
        $display("Applying reset...");
        #12 rst = 1;   // release reset

        // Run counter
        #100;

        // Apply reset again
        $display("Resetting again...");
        rst = 0;
        #10 rst = 1;

        // Run more cycles
        #100;

        $finish;
    end

    // Monitor
    initial begin
        $monitor("Time=%0t | rst=%b | count=%d", $time, rst, count);
    end

    // Dump for GTKWave
    initial begin
        $dumpfile("counter_tb.vcd");
        $dumpvars(0, counter_basic_tb);
    end

endmodule

Counter/counter_tb.vcd
$date
	Mon Sep 01 22:50:02 2025
$end
$version
	Icarus Verilog
$end
$timescale
	1ps
$end
$scope module counter_basic_tb $end
$var wire 8 ! count [7:0] $end
$var reg 1 " clk $end
$var reg 1 # rst $end
$scope module uut $end
$var wire 1 " clk $end
$var wire 8 $ count [7:0] $end
$var wire 1 # rst $end
$var reg 8 % count_temp [7:0] $end
$upscope $end
$upscope $end
$enddefinitions $end
#0
$dumpvars
bx %
bx $
0#
0"
bx !
$end
#5000
b0 !
b0 $
b0 %
1"
#10000
0"
#12000
1#
#15000
b1 !
b1 $
b1 %
1"
#20000
0"
#25000
b10 !
b10 $
b10 %
1"
#30000
0"
#35000
b11 !
b11 $
b11 %
1"
#40000
0"
#45000
b100 !
b100 $
b100 %
1"
#50000
0"
#55000
b101 !
b101 $
b101 %
1"
#60000
0"
#65000
b110 !
b110 $
b110 %
1"
#70000
0"
#75000
b111 !
b111 $
b111 %
1"
#80000
0"
#85000
b1000 !
b1000 $
b1000 %
1"
#90000
0"
#95000
b1001 !
b1001 $
b1001 %
1"
#100000
0"
#105000
b1010 !
b1010 $
b1010 %
1"
#110000
0"
#112000
0#
#115000
b0 !
b0 $
b0 %
1"
#120000
0"
#122000
1#
#125000
b1 !
b1 $
b1 %
1"
#130000
0"
#135000
b10 !
b10 $
b10 %
1"
#140000
0"
#145000
b11 !
b11 $
b11 %
1"
#150000
0"
#155000
b100 !
b100 $
b100 %
1"
#160000
0"
#165000
b101 !
b101 $
b101 %
1"
#170000
0"
#175000
b110 !
b110 $
b110 %
1"
#180000
0"
#185000
b111 !
b111 $
b111 %
1"
#190000
0"
#195000
b1000 !
b1000 $
b1000 %
1"
#200000
0"
#205000
b1001 !
b1001 $
b1001 %
1"
#210000
0"
#215000
b1010 !
b1010 $
b1010 %
1"
